LICENSE
setup.py
bkash_payment.egg-info/PKG-INFO
bkash_payment.egg-info/SOURCES.txt
bkash_payment.egg-info/dependency_links.txt
bkash_payment.egg-info/requires.txt
bkash_payment.egg-info/top_level.txt
bkash_python/__init__.py
bkash_python/_constants.py
bkash_python/payment.py