Metadata-Version: 2.1
Name: bkash-payment
Version: 0.0.1
Summary: Implements SSLCOMMERZ payment gateway in python based web apps.
Author: V3n0m
Author-email: asfrabi15@gmail.com
Classifier: Programming Language :: Python :: 3
Classifier: License :: OSI Approved :: MIT License
Classifier: Operating System :: OS Independent
Requires-Python: >=3.6
License-File: LICENSE
